LICENSE
README.md
setup.py
lightningflower/__init__.py
lightningflower/client.py
lightningflower/config.py
lightningflower/data.py
lightningflower/model.py
lightningflower/server.py
lightningflower/strategy.py
lightningflower/utility.py
lightningflower.egg-info/PKG-INFO
lightningflower.egg-info/SOURCES.txt
lightningflower.egg-info/dependency_links.txt
lightningflower.egg-info/requires.txt
lightningflower.egg-info/top_level.txt