Metadata-Version: 2.1
Name: lightningflower
Version: 0.1.7
Summary: Pre-packaged federated learning framework using Flower and PyTorch-Lightning.
Home-page: https://github.com/ManuelRoeder/lightningflower
Author: Manuel Roeder
Author-email: manuel.roeder@web.de
License: MIT
Platform: UNKNOWN
Classifier: Development Status :: 3 - Alpha
Classifier: Intended Audience :: Science/Research
Classifier: License :: OSI Approved :: MIT License
Classifier: Operating System :: OS Independent
Classifier: Programming Language :: Python :: 3.8
Classifier: Topic :: Scientific/Engineering :: Artificial Intelligence
Requires-Python: >=3.8.12
License-File: LICENSE
